communityid/__init__.py
communityid/algo.py
communityid/compat.py
communityid/error.py
communityid/icmp.py
communityid/icmp6.py
communityid-1.5.0.data/scripts/community-id
communityid-1.5.0.data/scripts/community-id-pcap
communityid-1.5.0.data/scripts/community-id-pcapfilter
communityid-1.5.0.data/scripts/community-id-tcpdump
communityid-1.5.0.dist-info/LICENSE
communityid-1.5.0.dist-info/METADATA
communityid-1.5.0.dist-info/WHEEL
communityid-1.5.0.dist-info/top_level.txt
communityid-1.5.0.dist-info/RECORD
