Metadata-Version: 2.1
Name: communityid
Version: 1.5.0
Summary: Community ID flow hashing
Home-page: https://github.com/corelight/pycommunityid
Author: Christian Kreibich
Author-email: christian@corelight.com
License: BSD
Platform: UNKNOWN
Classifier: Programming Language :: Python :: 3
Classifier: License :: OSI Approved :: BSD License
Classifier: Operating System :: OS Independent
License-File: LICENSE
